{
  "node_id": "68f3c941-8bc0-48af-8c8e-c18e88e040c2",
  "node_type": "entity_state",
  "content": "shoes2 is a shoes with attributes [white sneakers with black laces: white sneakers with black laces] at position (39.6, 433.6)",
  "tau": [
    0,
    66
  ],
  "metadata": {
    "entity_tag": "shoes2",
    "label": "shoes",
    "attributes": {
      "white sneakers with black laces": "white sneakers with black laces"
    },
    "layer_id": 2,
    "layer_mapping": [],
    "frame_start": 0,
    "latest_bbox": [
      33.914,
      426.384,
      45.338,
      440.785
    ]
  },
  "is_tombstone": false,
  "parent_ids": []
}